CONTRIBUTING.md
Jenkinsfile
MANIFEST.in
README.rst
TODO.rst
setup.cfg
setup.py
buildouts/plone4/buildout.cfg
buildouts/plone4/install.sh
buildouts/plone4/versions.cfg
docs/HISTORY.txt
docs/LICENSE.GPL
docs/LICENSE.txt
eea/__init__.py
eea.uberlisting.egg-info/PKG-INFO
eea.uberlisting.egg-info/SOURCES.txt
eea.uberlisting.egg-info/dependency_links.txt
eea.uberlisting.egg-info/entry_points.txt
eea.uberlisting.egg-info/namespace_packages.txt
eea.uberlisting.egg-info/not-zip-safe
eea.uberlisting.egg-info/requires.txt
eea.uberlisting.egg-info/top_level.txt
eea/uberlisting/README.txt
eea/uberlisting/__init__.py
eea/uberlisting/configure.zcml
eea/uberlisting/permissions.zcml
eea/uberlisting/profiles.zcml
eea/uberlisting/skins.zcml
eea/uberlisting/tests.py
eea/uberlisting/version.txt
eea/uberlisting/Extensions/install.py
eea/uberlisting/browser/__init__.py
eea/uberlisting/browser/configure.zcml
eea/uberlisting/browser/app/__init__.py
eea/uberlisting/browser/app/adapter.py
eea/uberlisting/browser/app/forms.py
eea/uberlisting/browser/app/interfaces.py
eea/uberlisting/browser/app/view.py
eea/uberlisting/browser/app/vocabularies.py
eea/uberlisting/browser/css/uberlisting_view.css
eea/uberlisting/browser/js/uberlisting_view.js
eea/uberlisting/locales/eea.pot
eea/uberlisting/locales/update.sh
eea/uberlisting/profiles/default/actions.xml
eea/uberlisting/profiles/default/cssregistry.xml
eea/uberlisting/profiles/default/jsregistry.xml
eea/uberlisting/profiles/default/metadata.xml
eea/uberlisting/profiles/default/rolemap.xml
eea/uberlisting/profiles/default/skins.xml
eea/uberlisting/profiles/default/types/Folder.xml
eea/uberlisting/profiles/uninstall/actions.xml
eea/uberlisting/profiles/uninstall/cssregistry.xml
eea/uberlisting/profiles/uninstall/eea.uberlisting.uninstall.txt
eea/uberlisting/profiles/uninstall/jsregistry.xml
eea/uberlisting/profiles/uninstall/skins.xml
eea/uberlisting/profiles/uninstall/types/Folder.xml
eea/uberlisting/skins/uberlisting_imgs/ajax-loader.gif
eea/uberlisting/skins/uberlisting_imgs/all_content.png
eea/uberlisting/skins/uberlisting_imgs/all_content.png.metadata
eea/uberlisting/skins/uberlisting_imgs/atct_album_view.png
eea/uberlisting/skins/uberlisting_imgs/atct_album_view.png.metadata
eea/uberlisting/skins/uberlisting_imgs/atct_topic_view.png
